[
  {
    "id": 1,
    "q": "在TCP/IP协议栈中，IPsec协议通常工作在哪一层，以提供端到端的安全服务？",
    "opts": ["应用层", "传输层", "数据链路层", "网络层"],
    "answer": 3,
    "explain": "IPsec（Internet Protocol Security）是用来保证IP通信安全的协议，它工作在TCP/IP协议的网络层。",
    "video": "http://www.midkey.xyz"
  },
  {
    "id": 2,
    "q": "RSA公钥密码体制的安全性主要基于哪个数学难题？",
    "opts": ["离散对数问题", "大整数因子分解问题", "椭圆曲线离散对数问题", "背包问题"],
    "answer": 1,
    "explain": "RSA的安全性基于将两个大素数相乘很容易，但对其乘积进行因数分解很难的数学原理。",
    "video": "http://www.midkey.xyz"
  },
  {
    "id": 3,
    "q": "Bell-LaPadula模型中，主体（Subject）只能读取安全级别低于或等于自身的客体，而只能写入安全级别高于或等于自身的客体，这被称为？",
    "opts": ["隔离原则", "最小特权原则", "简单安全属性与*属性", "责任分离原则"],
    "answer": 2,
    "explain": "简单安全属性（Simple Security Property）对应于“不能读高”（No Read Up），*属性（Star Property）对应于“不能写低”（No Write Down），它们是Bell-LaPadula模型中用于保护机密性的核心规则。",
    "video": "http://www.midkey.xyz"
  },
  {
    "id": 4,
    "q": "哪种类型的恶意软件在感染系统后，会加密用户文件并要求支付赎金才能解锁？",
    "opts": ["特洛伊木马（Trojan Horse）", "蠕虫（Worm）", "勒索软件（Ransomware）", "间谍软件（Spyware）"],
    "answer": 2,
    "explain": "勒索软件（Ransomware）的典型行为是加密受害者的数据，然后索要赎金以提供解密密钥。",
    "video": "http://www.midkey.xyz"
  },
  {
    "id": 5,
    "q": "针对SQL注入攻击，最有效的预防措施是？",
    "opts": ["过滤用户输入中的特殊字符", "使用存储过程（Stored Procedure）和参数化查询（Prepared Statements）", "将数据库端口设置为非标准端口", "限制用户输入长度"],
    "answer": 1,
    "explain": "参数化查询将SQL代码与用户数据分离，即使数据中包含恶意SQL语句，也不会被数据库引擎作为可执行代码处理，是防御SQL注入的最佳方法。",
    "video": "http://www.midkey.xyz"
  },
  {
    "id": 6,
    "q": "ISO/IEC 27001标准主要关注的是？",
    "opts": ["信息安全管理体系（ISMS）", "信息系统审计", "灾难恢复计划", "风险评估方法"],
    "answer": 0,
    "explain": "ISO/IEC 27001是建立、实施、保持和持续改进信息安全管理体系（ISMS）的国际标准。",
    "video": "http://www.midkey.xyz"
  },
  {
    "id": 7,
    "q": "IDS（入侵检测系统）和IPS（入侵防御系统）的主要区别在于？",
    "opts": ["IDS只能监控网络流量，IPS可以监控主机活动", "IDS只记录告警，IPS可以实时阻断攻击", "IDS工作在网络层，IPS工作在应用层", "IDS通常部署在内网，IPS通常部署在外网"],
    "answer": 1,
    "explain": "IDS的职责是检测并告警，而IPS则更进一步，可以在检测到攻击时主动采取行动进行防御和阻断。",
    "video": "http://www.midkey.xyz"
  },
  {
    "id": 8,
    "q": "在身份认证中，哪种因素属于“你是什么”（Something You Are）？",
    "opts": ["密码", "动态令牌", "指纹识别", "私钥文件"],
    "answer": 2,
    "explain": "身份认证的三要素包括：你知道什么（密码、PIN）、你有什么（令牌、手机）和你是什么（生物特征，如指纹、虹膜）。",
    "video": "http://www.midkey.xyz"
  },
  {
    "id": 9,
    "q": "在安全域划分中，通常将面向互联网的服务器（如Web Server）放置在哪个区域？",
    "opts": ["内部网络（Intranet）", "非军事化区（DMZ）", "核心网络（Core Network）", "运维管理区"],
    "answer": 1,
    "explain": "DMZ（Demilitarized Zone，非军事化区）是用于隔离公共访问的服务（如Web、邮件）和内部私有网络的安全区域。",
    "video": "http://www.midkey.xyz"
  },
  {
    "id": 10,
    "q": "下列哪一项是分组密码（Block Cipher）的工作模式，它支持并行加密并且不会将一个加密错误传播到后续分组？",
    "opts": ["CBC (Cipher Block Chaining)", "ECB (Electronic Codebook)", "CFB (Cipher Feedback)", "CTR (Counter)"],
    "answer": 3,
    "explain": "CTR（Counter Mode）将分组密码转换为流密码，每个分组的加密与之前的分组无关，因此支持并行处理且错误不会传播。",
    "video": "http://www.midkey.xyz"
  },
  {
    "id": 11,
    "q": "数字签名主要用于提供信息的哪种安全服务？",
    "opts": ["保密性（Confidentiality）", "可用性（Availability）", "完整性（Integrity）和不可否认性（Non-repudiation）", "访问控制（Access Control）"],
    "answer": 2,
    "explain": "数字签名通过证明数据源和确保数据未被篡改，来提供完整性和不可否认性。",
    "video": "http://www.midkey.xyz"
  },
  {
    "id": 12,
    "q": "在虚拟化环境中，攻击者突破虚拟机监控器（Hypervisor）的隔离，获取对底层操作系统或硬件的控制权，这种攻击被称为？",
    "opts": ["容器劫持", "拒绝服务攻击", "虚拟机逃逸（VM Escape）", "侧信道攻击"],
    "answer": 2,
    "explain": "虚拟机逃逸（VM Escape）是指攻击者通过利用Hypervisor的漏洞，从一个虚拟机中获取对Hypervisor或宿主机的控制权。",
    "video": "http://www.midkey.xyz"
  },
  {
    "id": 13,
    "q": "风险评估中的“三要素”通常指的是？",
    "opts": ["资产、威胁、漏洞", "保密性、完整性、可用性", "人、过程、技术", "预算、时间、范围"],
    "answer": 0,
    "explain": "信息安全风险的计算公式通常为：风险 = 资产价值 $\\times$ (威胁 $\\times$ 漏洞)。",
    "video": "http://www.midkey.xyz"
  },
  {
    "id": 14,
    "q": "在Linux系统中，用于设置文件权限（如 rwx）的命令是？",
    "opts": ["`ls -l`", "`chmod`", "`chown`", "`netstat`"],
    "answer": 1,
    "explain": "`chmod`命令（Change Mode）用于改变文件或目录的访问权限，而`ls -l`用于查看权限，`chown`用于改变所有者。",
    "video": "http://www.midkey.xyz"
  },
  {
    "id": 15,
    "q": "哪种日志类型对于分析攻击者在系统内部的横向移动轨迹最为重要？",
    "opts": ["Web服务器访问日志", "防火墙拒绝日志", "终端设备的DNS查询日志", "操作系统登录与进程创建日志"],
    "answer": 3,
    "explain": "横向移动通常涉及使用窃取的凭证在不同主机上登录或执行新进程，因此操作系统级的登录和进程日志是分析此行为的关键。",
    "video": "http://www.midkey.xyz"
  },
  {
    "id": 16,
    "q": "渗透测试中，如果测试人员被授权以一个普通内部员工的身份（拥有部分信息）进行测试，这种测试类型被称为？",
    "opts": ["黑盒测试（Black Box）", "白盒测试（White Box）", "灰盒测试（Gray Box）", "盲测（Blind Test）"],
    "answer": 2,
    "explain": "灰盒测试（Gray Box）是介于黑盒（无内部信息）和白盒（完全了解内部细节）之间的一种测试，测试人员拥有部分系统知识或凭证。",
    "video": "http://www.midkey.xyz"
  },
  {
    "id": 17,
    "q": "RTO（Recovery Time Objective）在灾难恢复计划中的含义是？",
    "opts": ["数据丢失的最大可接受量", "系统恢复到可用状态所需的最长时间", "两次备份之间的时间间隔", "业务连续性计划的成本"],
    "answer": 1,
    "explain": "RTO（恢复时间目标）是指系统或业务流程中断后，必须恢复到可用状态所允许的最长停机时间。数据丢失的最大可接受量是RPO（Recovery Point Objective）。",
    "video": "http://www.midkey.xyz"
  },
  {
    "id": 18,
    "q": "捕获网络数据包后，用于查看和分析数据包内容的常用工具是？",
    "opts": ["Nmap", "Metasploit", "Wireshark", "Burp Suite"],
    "answer": 2,
    "explain": "Wireshark是一款强大的网络协议分析器，能够实时捕获和详细检查网络数据包的内容和结构。",
    "video": "http://www.midkey.xyz"
  },
  {
    "id": 19,
    "q": "在公钥基础设施（PKI）中，负责颁发、管理和撤销数字证书的实体是？",
    "opts": ["注册机构（RA）", "证书持有者", "认证机构（CA）", "用户"],
    "answer": 2,
    "explain": "认证机构（CA，Certificate Authority）是PKI的核心，负责验证身份、颁发、管理和撤销数字证书。",
    "video": "http://www.midkey.xyz"
  },
  {
    "id": 20,
    "q": "SPF（Sender Policy Framework）记录的主要作用是防止哪种类型的攻击？",
    "opts": ["拒绝服务攻击（DoS）", "邮件内容篡改", "邮件钓鱼/伪造发件人地址", "病毒传播"],
    "answer": 2,
    "explain": "SPF是一种电子邮件验证标准，允许域所有者指定哪些IP地址可以代表该域发送邮件，从而有效防止邮件发件人地址伪造（欺骗）。",
    "video": "http://www.midkey.xyz"
  },


  {
    "id": 21,
    "q": "以下哪种攻击利用了网络会话中的信任关系，诱骗受害者执行非本意的操作？",
    "opts": ["SQL注入（SQL Injection）", "跨站请求伪造（CSRF）", "缓冲区溢出（Buffer Overflow）", "文件上传漏洞"],
    "answer": 1,
    "explain": "CSRF攻击（Cross-Site Request Forgery）利用用户在某一网站的认证信息，诱骗其浏览器向该网站发送恶意请求。",
    "video": "http://www.midkey.xyz"
  },
  {
    "id": 22,
    "q": "下列哪种安全机制主要用于防止数据在存储或传输过程中被未授权方窃取？",
    "opts": ["访问控制列表（ACL）", "完整性校验（Hash）", "数据加密（Encryption）", "负载均衡"],
    "answer": 2,
    "explain": "加密是对数据进行编码，使其只有拥有密钥的授权用户才能读取，从而保障数据的机密性，防止数据被窃取。",
    "video": "http://www.midkey.xyz"
  },
  {
    "id": 23,
    "q": "在对称加密算法中，哪一个不是常见的算法？",
    "opts": ["AES", "DES", "3DES", "DSA"],
    "answer": 3,
    "explain": "DSA（Digital Signature Algorithm）是数字签名算法，属于非对称密码学范畴。AES、DES和3DES都是对称加密算法。",
    "video": "http://www.midkey.xyz"
  },
  {
    "id": 24,
    "q": "操作系统中的最小权限原则（Principle of Least Privilege）指的是：",
    "opts": ["只允许系统管理员访问所有资源", "用户只能拥有完成工作所需的最小权限集", "所有用户默认拥有相同的权限", "定期审计所有用户的权限"],
    "answer": 1,
    "explain": "最小权限原则要求授予用户或进程完成其工作所需的最低限度的访问权限，以减少攻击面和损害范围。",
    "video": "http://www.midkey.xyz"
  },
  {
    "id": 25,
    "q": "哪个协议在应用层提供安全的远程命令行访问，以替代不安全的Telnet？",
    "opts": ["FTP", "SMTP", "SSH", "HTTP"],
    "answer": 2,
    "explain": "SSH（Secure Shell）是一种加密的网络协议，用于在不安全的网络上安全地进行远程登录和执行命令。",
    "video": "http://www.midkey.xyz"
  },
  {
    "id": 26,
    "q": "信息安全的三要素（CIA三元组）不包括以下哪一项？",
    "opts": ["机密性（Confidentiality）", "可用性（Availability）", "可审计性（Audibility）", "完整性（Integrity）"],
    "answer": 2,
    "explain": "信息安全三要素是机密性、完整性和可用性（Confidentiality, Integrity, Availability）。可审计性是重要的安全目标，但不属于CIA三元组的核心要素。",
    "video": "http://www.midkey.xyz"
  },
  {
    "id": 27,
    "q": "下列哪个IP地址范围通常用于私有网络（Private Network）？",
    "opts": ["172.16.0.0/12", "169.254.0.0/16", "10.0.0.0/8", "192.168.0.0/16"],
    "answer": 0,
    "explain": "私有地址空间包括三个CIDR块：A类私有地址10.0.0.0/8；B类私有地址172.16.0.0/12；C类私有地址192.168.0.0/16。选项中172.16.0.0/12是正确的B类私有地址范围。",
    "video": "http://www.midkey.xyz"
  },
  {
    "id": 28,
    "q": "下列哪种漏洞允许攻击者在目标应用程序的内存中执行恶意代码？",
    "opts": ["逻辑漏洞", "配置错误", "缓冲区溢出", "跨站脚本（XSS）"],
    "answer": 2,
    "explain": "缓冲区溢出（Buffer Overflow）是指程序向缓冲区写入数据时，超出了缓冲区本身的容量，溢出部分的数据覆盖了相邻的内存区域，可能导致恶意代码执行。",
    "video": "http://www.midkey.xyz"
  },
  {
    "id": 29,
    "q": "灾难恢复计划（DRP）中，RPO（Recovery Point Objective）的含义是？",
    "opts": ["系统恢复所需的最长时间", "两次备份之间的时间间隔", "数据丢失的最大可接受量", "业务中断造成的最大损失"],
    "answer": 2,
    "explain": "RPO（恢复点目标）指的是业务能够承受的最大数据损失量，决定了备份或复制数据的频率。",
    "video": "http://www.midkey.xyz"
  },
  {
    "id": 30,
    "q": "哪种攻击是针对 DNS 服务器的，旨在将域名解析到错误的（恶意）IP地址？",
    "opts": ["SYN Flood", "ARP欺骗", "DNS缓存投毒（Cache Poisoning）", "Smurf攻击"],
    "answer": 2,
    "explain": "DNS缓存投毒攻击通过注入错误的DNS信息到DNS解析器中，使得后续的用户请求被重定向到攻击者控制的网站。",
    "video": "http://www.midkey.xyz"
  },
  {
    "id": 31,
    "q": "数字证书中不包含以下哪一项信息？",
    "opts": ["证书持有者的公钥", "CA的数字签名", "私钥", "证书的有效期"],
    "answer": 2,
    "explain": "数字证书（X.509）中包含公钥，但绝不包含私钥。私钥由证书持有者安全保存，用于解密或签名。",
    "video": "http://www.midkey.xyz"
  },
  {
    "id": 32,
    "q": "哪个工具最常用于在渗透测试中对目标主机进行端口扫描和操作系统指纹识别？",
    "opts": ["Wireshark", "Burp Suite", "Nmap", "Metasploit"],
    "answer": 2,
    "explain": "Nmap（Network Mapper）是用于网络发现和安全审计的免费开源工具，常用于探测主机、服务和操作系统。",
    "video": "http://www.midkey.xyz"
  },
  {
    "id": 33,
    "q": "防火墙的下列哪种类型能够检查会话状态并决定是否允许后续的数据包通过？",
    "opts": ["包过滤防火墙（Packet Filtering）", "应用层网关防火墙（Application-Level Gateway）", "状态检测防火墙（Stateful Inspection）", "透明防火墙"],
    "answer": 2,
    "explain": "状态检测防火墙记录了所有TCP/UDP会话的状态信息，只允许与已有会话相关的返回数据包通过，提供了更高的安全性。",
    "video": "http://www.midkey.xyz"
  },
  {
    "id": 34,
    "q": "在密码学中，哪种概念指的是哈希函数具有的特性，即找到两条不同的输入得到相同的输出是计算上不可行的？",
    "opts": ["不可逆性", "抗弱碰撞性", "抗强碰撞性", "确定性"],
    "answer": 2,
    "explain": "抗强碰撞性（Strong Collision Resistance）是指找到两个不同的输入 $x \\ne y$ 使得 $H(x) = H(y)$ 在计算上不可行。",
    "video": "http://www.midkey.xyz"
  },
  {
    "id": 35,
    "q": "下列哪项措施最能防御钓鱼邮件（Phishing Email）？",
    "opts": ["安装杀毒软件", "定期更换复杂的WIFI密码", "培训员工识别可疑邮件和不点击陌生链接", "限制对内部服务器的物理访问"],
    "answer": 2,
    "explain": "钓鱼邮件攻击主要利用社会工程学，对员工进行安全意识培训是防御此类攻击的最重要防线。",
    "video": "http://www.midkey.xyz"
  },
  {
    "id": 36,
    "q": "在云安全责任共担模型中，对于SaaS（软件即服务）应用，谁通常负责应用配置的安全？",
    "opts": ["云服务提供商（CSP）", "第三方审计机构", "客户", "硬件供应商"],
    "answer": 2,
    "explain": "在SaaS模型中，CSP负责基础设施、操作系统、运行时等，但应用层面（如用户权限设置、数据输入和配置）的安全责任通常由客户承担。",
    "video": "http://www.midkey.xyz"
  },
  {
    "id": 37,
    "q": "如果一个网站的登录凭证是以明文形式通过HTTP传输的，那么它最容易受到哪种攻击？",
    "opts": ["文件包含漏洞", "拒绝服务（DoS）", "中间人攻击（MITM）", "跨站脚本（XSS）"],
    "answer": 2,
    "explain": "使用HTTP明文传输数据，攻击者在同一网络中可以利用中间人攻击（MITM）轻松嗅探到传输的数据，如登录凭证。",
    "video": "http://www.midkey.xyz"
  },
  {
    "id": 38,
    "q": "Kerberos认证系统主要用于提供哪种安全服务？",
    "opts": ["数据加密", "单点登录（Single Sign-On, SSO）", "网络数据包过滤", "入侵检测"],
    "answer": 1,
    "explain": "Kerberos是一种网络认证协议，旨在通过安全的密钥交换，为客户端和服务器应用提供强大的认证机制，是实现单点登录（SSO）的基础。",
    "video": "http://www.midkey.xyz"
  },
  {
    "id": 39,
    "q": "在安全审计中，对某个系统的漏洞进行评估和利用，以确定其当前安全状态的过程被称为？",
    "opts": ["风险分析", "基线配置", "渗透测试", "配置管理"],
    "answer": 2,
    "explain": "渗透测试（Penetration Testing）是一种主动的安全评估方法，通过模拟黑客攻击来发现和验证系统中的安全漏洞。",
    "video": "http://www.midkey.xyz"
  },
  {
    "id": 40,
    "q": "PKI体系结构中的CA（认证机构）在颁发证书之前，必须对用户身份进行验证，通常由哪个机构协助完成？",
    "opts": ["证书持有者", "注册机构（RA）", "信任锚", "审计机构"],
    "answer": 1,
    "explain": "注册机构（RA，Registration Authority）负责验证证书申请人的身份，并将验证后的请求提交给CA进行证书的签发。",
    "video": "http://www.midkey.xyz"
  },
  {
    "id": 41,
    "q": "哪个是用于对Web应用程序进行安全测试的集成平台，常用于拦截、查看和修改HTTP请求？",
    "opts": ["Nessus", "Metasploit", "Aircrack-ng", "Burp Suite"],
    "answer": 3,
    "explain": "Burp Suite是Web应用安全测试中功能最全面的工具之一，其代理功能允许拦截和修改客户端与服务器之间的HTTP/HTTPS流量。",
    "video": "http://www.midkey.xyz"
  },
  {
    "id": 42,
    "q": "当发生安全事件后，取证人员应首先采取以下哪一操作来保护现场？",
    "opts": ["立即重启受感染的计算机", "断开网络连接并记录系统状态", "删除日志文件以防泄漏", "修改被感染的文件权限"],
    "answer": 1,
    "explain": "在安全取证中，首要任务是保护易失性证据，通过断开网络连接来防止数据丢失和攻击者进一步操作，并记录下内存、进程等系统状态。",
    "video": "http://www.midkey.xyz"
  },
  {
    "id": 43,
    "q": "在TLS/SSL握手过程中，客户端验证服务器身份的关键步骤是？",
    "opts": ["客户端发送它的公钥", "服务器发送它的私钥", "客户端验证服务器证书的链和签名", "双方计算会话密钥"],
    "answer": 2,
    "explain": "客户端收到服务器证书后，会检查证书是否过期，是否被CA信任，并验证证书上的数字签名以确认服务器的身份。",
    "video": "http://www.midkey.xyz"
  },
  {
    "id": 44,
    "q": "哪种技术可以用于在不安全网络上建立一个安全的、加密的通信隧道？",
    "opts": ["NAT", "VPN", "ARP", "DHCP"],
    "answer": 1,
    "explain": "VPN（Virtual Private Network，虚拟专用网络）通过在公共网络上建立加密隧道，实现远程用户或分支机构的安全接入。",
    "video": "http://www.midkey.xyz"
  },
  {
    "id": 45,
    "q": "下列哪项关于DDoS（分布式拒绝服务）攻击的描述是正确的？",
    "opts": ["它通常只针对网络协议层", "它利用单个攻击源向目标发送大量请求", "它利用多个受控主机同时攻击单一目标", "它旨在窃取敏感数据"],
    "answer": 2,
    "explain": "DDoS攻击使用大量的、分布在不同位置的受控主机（僵尸网络）同时向目标系统发起请求，从而耗尽其资源，导致服务不可用。",
    "video": "http://www.midkey.xyz"
  },
  {
    "id": 46,
    "q": "当用户在Web应用中提交的数据未经过滤或转义，直接插入到HTML页面中时，可能导致哪种攻击？",
    "opts": ["CSRF", "XSS", "DoS", "RCE"],
    "answer": 1,
    "explain": "XSS（Cross-Site Scripting，跨站脚本）攻击正是利用了应用程序对用户输入数据的不当处理，在浏览器中执行恶意脚本。",
    "video": "http://www.midkey.xyz"
  },
  {
    "id": 47,
    "q": "以下哪种身份认证方式，其本质属于“你拥有什么”（Something You Have）？",
    "opts": ["指纹识别", "密码", "动态令牌（Token）", "问题/答案"],
    "answer": 2,
    "explain": "动态令牌（如硬件Token、手机应用生成的动态码）是用户拥有的物理或逻辑设备，用于生成一次性密码进行身份验证。",
    "video": "http://www.midkey.xyz"
  },
  {
    "id": 48,
    "q": "一个良好的安全策略应该具备的特性不包括以下哪一项？",
    "opts": ["易于理解和实施", "能够保护所有资产不受任何威胁", "与业务目标保持一致", "定义清晰的责任和权限"],
    "answer": 1,
    "explain": "任何安全策略都无法绝对保证所有资产不受任何威胁（即不可能达到零风险）。安全策略应侧重于合理管理风险。",
    "video": "http://www.midkey.xyz"
  },
  {
    "id": 49,
    "q": "公钥密码体制中，发送方使用接收方的什么来加密信息？",
    "opts": ["发送方的公钥", "发送方的私钥", "接收方的私钥", "接收方的公钥"],
    "answer": 3,
    "explain": "在公钥加密中，为了保证信息的机密性，发送方使用接收方的公钥加密，只有接收方拥有的私钥才能解密。",
    "video": "http://www.midkey.xyz"
  },
  {
    "id": 50,
    "q": "在信息安全管理体系（ISMS）中，PDCA循环中的“A”代表什么？",
    "opts": ["分析（Analysis）", "行动（Act）", "审计（Audit）", "意识（Awareness）"],
    "answer": 1,
    "explain": "PDCA是持续改进的管理模型，包括计划（Plan）、实施（Do）、检查（Check）和行动（Act），'Act'指采取措施以持续改进体系。",
    "video": "http://www.midkey.xyz"
  },
  

  {
    "id": 51,
    "q": "以下哪一项是信息安全审计的主要目的？",
    "opts": ["发现新的零日漏洞", "确保安全控制措施符合政策和法规要求", "实时阻止正在发生的网络攻击", "设计系统的物理安全架构"],
    "answer": 1,
    "explain": "信息安全审计是对组织的安全策略、流程和控制措施进行独立评估，以确定其是否有效、符合既定标准和法规要求。",
    "video": "http://www.midkey.xyz"
  },
  {
    "id": 52,
    "q": "哪种加密算法通过使用一个较短的密钥加密数据块，并且对每个块使用一个不同的初始化向量（IV）来增强安全性？",
    "opts": ["DES", "AES", "IDEA", "RC4"],
    "answer": 1,
    "explain": "AES（Advanced Encryption Standard）是目前最常用的分组对称加密标准，支持128/192/256位的密钥长度，通常配合CBC、GCM等工作模式使用。",
    "video": "http://www.midkey.xyz"
  },
  {
    "id": 53,
    "q": "下列哪种认证技术旨在解决“密码重放攻击”（Replay Attack）的问题？",
    "opts": ["静态密码", "双因素认证（MFA）", "一次性密码（OTP）", "指纹识别"],
    "answer": 2,
    "explain": "一次性密码（OTP）每次使用后即失效，即使攻击者截获了该密码，也无法用于未来的认证，从而有效防止重放攻击。",
    "video": "http://www.midkey.xyz"
  },
  {
    "id": 54,
    "q": "哪种攻击利用了Web服务器处理上传文件时的缺陷，导致攻击者可以上传并执行恶意脚本或程序？",
    "opts": ["目录遍历（Directory Traversal）", "文件包含漏洞（File Inclusion）", "不安全的文件上传漏洞", "XML外部实体注入（XXE）"],
    "answer": 2,
    "explain": "不安全的文件上传漏洞允许攻击者绕过过滤机制，上传可执行文件到服务器，并最终执行，可能导致远程代码执行（RCE）。",
    "video": "http://www.midkey.xyz"
  },
  {
    "id": 55,
    "q": "以下关于恶意软件“蠕虫”（Worm）的描述，哪一项是其主要特征？",
    "opts": ["需要寄生于宿主文件才能运行", "通过利用网络漏洞进行自我复制和传播", "旨在窃取用户的银行卡信息", "只感染操作系统引导区"],
    "answer": 1,
    "explain": "蠕虫（Worm）最主要的特征是其独立性，它无需寄生于其他文件，能够利用网络或软件漏洞自行复制和传播到其他计算机。",
    "video": "http://www.midkey.xyz"
  },
  {
    "id": 56,
    "q": "哪个协议在数据链路层提供安全服务，主要用于保护局域网内无线网络的通信安全？",
    "opts": ["IPsec", "TLS", "WEP/WPA/WPA2", "SSH"],
    "answer": 2,
    "explain": "WEP、WPA、WPA2和WPA3都是用于加密和保护Wi-Fi（无线局域网）通信的安全协议，工作在数据链路层。",
    "video": "http://www.midkey.xyz"
  },
  {
    "id": 57,
    "q": "根据信息安全风险管理过程，在识别了资产、威胁和漏洞之后，下一步应该做什么？",
    "opts": ["实施安全控制措施", "风险评估（计算风险等级）", "制定安全策略", "进行渗透测试"],
    "answer": 1,
    "explain": "风险管理流程中，在识别要素（资产、威胁、漏洞）后，下一步是评估风险，即计算风险的严重程度和发生的可能性。",
    "video": "http://www.midkey.xyz"
  },
  {
    "id": 58,
    "q": "哪个安全控制措施属于物理安全范畴？",
    "opts": ["防火墙", "数据加密", "门禁系统和监控摄像头", "操作系统用户权限设置"],
    "answer": 2,
    "explain": "物理安全控制措施旨在保护信息系统的硬件和环境，门禁系统和监控摄像头是典型的物理访问控制。",
    "video": "http://www.midkey.xyz"
  },
  {
    "id": 59,
    "q": "在PKI体系中，用于验证证书是否仍然有效的在线协议是？",
    "opts": ["X.509", "CRL（Certificate Revocation List）", "OCSP（Online Certificate Status Protocol）", "MD5"],
    "answer": 2,
    "explain": "OCSP是一种用于获取证书撤销状态的实时协议，相比于CRL（证书撤销列表），它能提供更及时的状态信息。",
    "video": "http://www.midkey.xyz"
  },
  {
    "id": 60,
    "q": "下列哪种攻击主要通过发送大量伪造的SYN请求到服务器，占用连接资源，最终导致服务器无法响应正常请求？",
    "opts": ["Smurf攻击", "Ping of Death", "Land攻击", "SYN Flood"],
    "answer": 3,
    "explain": "SYN Flood（SYN洪泛）是一种经典的DDoS攻击，它利用TCP三次握手的漏洞，发送大量SYN包，使服务器处于等待状态，耗尽连接队列资源。",
    "video": "http://www.midkey.xyz"
  },
  {
    "id": 61,
    "q": "在软件开发生命周期（SDLC）中，哪个阶段应该最早引入安全需求和设计？",
    "opts": ["测试和部署阶段", "需求分析和设计阶段", "编码实现阶段", "维护阶段"],
    "answer": 1,
    "explain": "安全左移（Shift Left）原则强调安全活动应尽早介入SDLC，即在需求分析和设计阶段就考虑安全需求和风险。",
    "video": "http://www.midkey.xyz"
  },
  {
    "id": 62,
    "q": "哪个标准定义了信息安全管理体系（ISMS）的实施和维护指南？",
    "opts": ["ISO/IEC 27001", "ISO 9001", "GB/T 22080", "ISO/IEC 27002"],
    "answer": 3,
    "explain": "ISO/IEC 27002（以前的17799）提供了安全控制措施的实施指南和最佳实践，作为27001标准的补充。",
    "video": "http://www.midkey.xyz"
  },
  {
    "id": 63,
    "q": "为了防御Web应用中的逻辑漏洞，最有效的防御手段是？",
    "opts": ["输入过滤和输出编码", "使用参数化查询", "严格的业务流程和逻辑校验", "定期进行端口扫描"],
    "answer": 2,
    "explain": "逻辑漏洞涉及业务流程的不当设计，无法通过简单的技术手段（如过滤）修复，需要对业务逻辑进行严格的校验和控制。",
    "video": "http://www.midkey.xyz"
  },
  {
    "id": 64,
    "q": "在云计算模式中，IaaS（基础设施即服务）的客户对以下哪项拥有最高的安全控制权？",
    "opts": ["物理基础设施", "操作系统和应用", "Hypervisor", "网络连接"],
    "answer": 1,
    "explain": "IaaS客户负责其部署的操作系统、应用软件、配置数据等的安全。云提供商负责物理设施和底层虚拟化平台。",
    "video": "http://www.midkey.xyz"
  },
  {
    "id": 65,
    "q": "下列哪种技术可以确保数据在传输过程中不被篡改（数据完整性）？",
    "opts": ["对称加密", "数据脱敏", "数字签名和消息认证码（MAC）", "身份认证"],
    "answer": 2,
    "explain": "数字签名和消息认证码（MAC）都通过计算数据的哈希值并进行加密或加秘钥操作，来确保数据在传输后能被验证是否被修改。",
    "video": "http://www.midkey.xyz"
  },
  {
    "id": 66,
    "q": "在Linux系统中，哪个文件存储了本地用户的加密密码信息？",
    "opts": ["/etc/passwd", "/etc/group", "/etc/shadow", "/var/log/messages"],
    "answer": 2,
    "explain": "为了提高安全性，Linux将用户的加密密码信息从可公开读取的`/etc/passwd`文件转移到了只有root用户可访问的`/etc/shadow`文件中。",
    "video": "http://www.midkey.xyz"
  },
  {
    "id": 67,
    "q": "以下哪种攻击是社会工程学的一种形式，通过伪装成权威人士或可信实体来骗取敏感信息？",
    "opts": ["网络嗅探", "字典攻击", "钓鱼攻击", "拒绝服务攻击"],
    "answer": 2,
    "explain": "钓鱼攻击（Phishing）是典型的社会工程学手段，攻击者通过欺骗手段诱使用户泄露个人信息或凭证。",
    "video": "http://www.midkey.xyz"
  },
  {
    "id": 68,
    "q": "在设计高可用性系统时，通常会采用哪种备份或恢复指标，来量化系统在灾难发生后恢复到可接受状态所需的时间？",
    "opts": ["MTTR（平均恢复时间）", "MTBF（平均故障间隔时间）", "RPO（恢复点目标）", "RTO（恢复时间目标）"],
    "answer": 3,
    "explain": "RTO（Recovery Time Objective）是灾难恢复中的核心指标，用于衡量系统从故障发生到恢复正常运行状态所需的最长时间。",
    "video": "http://www.midkey.xyz"
  },
  {
    "id": 69,
    "q": "以下哪一项是基于主机（Host-based）的入侵检测系统（HIDS）的主要功能？",
    "opts": ["分析网络流量中的恶意数据包", "监控网络端口的开放状态", "分析操作系统日志、文件完整性和进程活动", "实时阻断来自外部的SYN Flood攻击"],
    "answer": 2,
    "explain": "HIDS安装在单个主机上，主要功能是监控该主机的内部活动，如系统日志、文件变化、用户登录和进程执行。",
    "video": "http://www.midkey.xyz"
  },
  {
    "id": 70,
    "q": "下列哪种密码攻击类型，攻击者拥有密文和与之对应的明文，目标是找到加密密钥？",
    "opts": ["唯密文攻击（Ciphertext-only Attack）", "已知明文攻击（Known-plaintext Attack）", "选择明文攻击（Chosen-plaintext Attack）", "中间相遇攻击（Meet-in-the-middle Attack）"],
    "answer": 1,
    "explain": "已知明文攻击中，攻击者拥有一些密文和它们对应的明文片段，利用这些信息来推导出加密密钥。",
    "video": "http://www.midkey.xyz"
  },
  {
    "id": 71,
    "q": "网络隔离中，将内部网络划分为多个独立子网，并强制在子网间进行安全检查的技术被称为？",
    "opts": ["VLAN", "网络虚拟化", "网络分段（Segmentation）", "网络地址转换（NAT）"],
    "answer": 2,
    "explain": "网络分段（Segmentation）是将一个大的网络分割成多个小的、相互隔离的子网或安全域，以限制攻击的横向移动。",
    "video": "http://www.midkey.xyz"
  },
  {
    "id": 72,
    "q": "以下哪个工具最适合用于在Web应用程序渗透测试中进行参数篡改和会话劫持？",
    "opts": ["Nmap", "Metasploit", "Wireshark", "Burp Suite"],
    "answer": 3,
    "explain": "Burp Suite的Proxy功能专门用于拦截和修改Web请求，是进行参数篡改、会话管理和漏洞扫描的主要工具。",
    "video": "http://www.midkey.xyz"
  },
  {
    "id": 73,
    "q": "为了防止员工通过个人设备接入公司网络造成数据泄露，组织应实施哪种安全策略？",
    "opts": ["ACL策略", "自带设备（BYOD）管理和控制", "VLAN隔离", "端口扫描"],
    "answer": 1,
    "explain": "BYOD（Bring Your Own Device）策略旨在规范和控制员工将个人设备带入工作环境所带来的安全风险，如数据访问和隔离。",
    "video": "http://www.midkey.xyz"
  },
  {
    "id": 74,
    "q": "以下哪个术语描述了一种程序或代码片段，它能够在受感染的系统中隐藏自身的活动和存在？",
    "opts": ["木马程序", "勒索软件", "Rootkit", "广告软件"],
    "answer": 2,
    "explain": "Rootkit是一组程序，设计用于隐藏恶意软件在操作系统中的存在和活动，以保持对系统的持久控制。",
    "video": "http://www.midkey.xyz"
  },
  {
    "id": 75,
    "q": "在密码学中，Diffie-Hellman算法主要用于解决哪个问题？",
    "opts": ["加密大量数据", "生成数字签名", "在不安全的信道上安全地协商共享密钥", "保护数据的完整性"],
    "answer": 2,
    "explain": "Diffie-Hellman密钥交换是一种允许双方在不安全的通信信道上协商出一个共享密钥的方法，该密钥随后可用于对称加密。",
    "video": "http://www.midkey.xyz"
  },
  {
    "id": 76,
    "q": "哪种攻击通常针对Web应用中的XML解析器，通过注入外部实体定义来访问敏感文件或执行拒绝服务？",
    "opts": ["CSRF", "XSS", "XXE", "RFI"],
    "answer": 2,
    "explain": "XXE（XML External Entity Injection，XML外部实体注入）攻击利用了XML解析器对外部实体引用的处理不当。",
    "video": "http://www.midkey.xyz"
  },
  {
    "id": 77,
    "q": "在信息安全管理中，以下哪一项措施属于'风险转移'策略？",
    "opts": ["购买网络安全保险", "投资部署IPS设备", "关闭不必要的服务", "提高员工安全意识"],
    "answer": 0,
    "explain": "风险转移（Risk Transfer）是将风险的财务后果转移给第三方，购买网络安全保险是最典型的风险转移措施。",
    "video": "http://www.midkey.xyz"
  },
  {
    "id": 78,
    "q": "访问控制模型中，哪一个模型是基于角色的，并为用户分配相应的角色以获得权限？",
    "opts": ["DAC（自主访问控制）", "MAC（强制访问控制）", "RBAC（基于角色的访问控制）", "ABAC（基于属性的访问控制）"],
    "answer": 2,
    "explain": "RBAC（Role-Based Access Control）通过定义角色及其权限，然后将用户分配给角色，简化了权限管理。",
    "video": "http://www.midkey.xyz"
  },
  {
    "id": 79,
    "q": "在密码学中，用于确保密钥、会话和数字证书长期安全的最佳实践是：",
    "opts": ["使用更快的算法", "定期更换密钥和证书", "将密钥存储在内存中", "禁用哈希函数"],
    "answer": 1,
    "explain": "定期更换加密密钥和数字证书是防止长期分析攻击、密钥泄露或算法老化导致安全失效的重要手段。",
    "video": "http://www.midkey.xyz"
  },
  {
    "id": 80,
    "q": "信息系统中用于集中收集、分析和管理安全事件日志数据的系统是？",
    "opts": ["DLP（数据防泄漏）", "IPS（入侵防御系统）", "SIEM（安全信息和事件管理）", "WAF（Web应用防火墙）"],
    "answer": 2,
    "explain": "SIEM系统（Security Information and Event Management）负责从网络设备、服务器和应用中收集日志，进行关联分析和告警。",
    "video": "http://www.midkey.xyz"
  },
  {
    "id": 81,
    "q": "下列哪种技术可以用于混淆或改变恶意代码的特征码，以逃避反病毒软件的检测？",
    "opts": ["静态分析", "多态/变形技术", "蜜罐技术", "流量镜像"],
    "answer": 1,
    "explain": "多态/变形（Polymorphic/Metamorphic）技术使恶意软件在每次感染或运行时改变其代码结构，但保持功能不变，从而躲避基于签名的检测。",
    "video": "http://www.midkey.xyz"
  },
  {
    "id": 82,
    "q": "在IPv6环境中，哪个协议常被用于实现端到端的安全通信，且是IPv6协议栈的强制组成部分？",
    "opts": ["ARP", "IPsec", "ICMP", "TCP"],
    "answer": 1,
    "explain": "IPsec（IP Security）协议在IPv4中是可选的，但在IPv6的原始设计中被列为强制组成部分（尽管实际部署中并不总是强制启用），用于提供认证和加密。",
    "video": "http://www.midkey.xyz"
  },
  {
    "id": 83,
    "q": "以下哪项是Web应用防火墙（WAF）的主要功能？",
    "opts": ["过滤网络层数据包", "防御SQL注入、XSS等应用层攻击", "防止操作系统级病毒感染", "为客户端提供安全远程接入"],
    "answer": 1,
    "explain": "WAF部署在Web服务器前，专门用于检测和阻断针对Web应用程序的特定攻击，如SQL注入、XSS和文件包含等。",
    "video": "http://www.midkey.xyz"
  },
  {
    "id": 84,
    "q": "在云计算和大数据环境中，对敏感数据进行替换或移除识别信息，使其无法追踪到原始数据主体的过程被称为？",
    "opts": ["数据备份", "数据脱敏/匿名化", "数据压缩", "数据同步"],
    "answer": 1,
    "explain": "数据脱敏（Data Masking）或匿名化是保护隐私的关键技术，旨在移除数据中的所有可识别信息，以防止泄露。",
    "video": "http://www.midkey.xyz"
  },
  {
    "id": 85,
    "q": "下列哪个是使用非对称加密算法进行数字签名的正确步骤？",
    "opts": ["发送方用接收方公钥加密哈希值", "发送方用自己的私钥加密哈希值", "发送方用自己的公钥加密数据", "发送方用接收方私钥加密数据"],
    "answer": 1,
    "explain": "数字签名是为了保证不可否认性，发送方使用自己的私钥对数据的哈希值进行加密，接收方使用发送方的公钥来验证签名。",
    "video": "http://www.midkey.xyz"
  },
  {
    "id": 86,
    "q": "在信息系统安全等级保护（等保）制度中，哪一层级适用于对国家安全、社会秩序和公共利益有特别重要影响的信息系统？",
    "opts": ["第二级（基本保护级）", "第三级（安全增强保护级）", "第四级（专门保护级）", "第五级（最高保护级）"],
    "answer": 3,
    "explain": "根据中国信息安全等级保护标准，第五级为最高保护级别，适用于对国家安全、社会秩序、公共利益造成特别严重损害的系统。",
    "video": "http://www.midkey.xyz"
  },
  {
    "id": 87,
    "q": "以下哪种安全漏洞是由于操作系统或应用程序没有正确验证用户提供的路径，可能导致访问受限文件？",
    "opts": ["缓冲区溢出", "目录遍历（Directory Traversal）", "XXE注入", "RCE（远程代码执行）"],
    "answer": 1,
    "explain": "目录遍历漏洞（也称路径遍历）允许攻击者使用`../`等序列，访问到应用程序根目录之外的系统文件或目录。",
    "video": "http://www.midkey.xyz"
  },
  {
    "id": 88,
    "q": "零信任（Zero Trust）安全模型的核心原则是？",
    "opts": ["相信内部网络，不相信外部网络", "永远不信任，始终验证", "信任所有经过身份认证的用户", "只信任预先配置的白名单设备"],
    "answer": 1,
    "explain": "零信任模型的关键在于“永远不信任，始终验证”（Never Trust, Always Verify），要求对任何试图访问资源的实体和流量都进行严格验证和授权。",
    "video": "http://www.midkey.xyz"
  },
  {
    "id": 89,
    "q": "在风险管理中，当识别到某项风险的可能性极低且影响有限时，通常采用哪种风险应对策略？",
    "opts": ["风险规避", "风险接受", "风险降低", "风险转移"],
    "answer": 1,
    "explain": "风险接受（Risk Acceptance）是指组织决定不采取任何行动来改变风险，通常用于可能性极低或影响极小的风险。",
    "video": "http://www.midkey.xyz"
  },
  {
    "id": 90,
    "q": "哪个协议可以用于在加密的通信中，客户端向服务器安全地发送用户名和密码进行身份验证？",
    "opts": ["IP", "LDAP", "CHAP", "ICMP"],
    "answer": 2,
    "explain": "CHAP（Challenge Handshake Authentication Protocol，挑战握手认证协议）在PPP连接中用于认证用户身份，它使用哈希函数，避免了在网络上传输明文密码。",
    "video": "http://www.midkey.xyz"
  },
  {
    "id": 91,
    "q": "以下哪项是基于网络（Network-based）的入侵检测系统（NIDS）的主要优势？",
    "opts": ["可以精确分析主机内部的进程活动", "只需少量部署就能覆盖整个网络", "不易受到攻击者对主机日志的篡改影响", "实时阻止来自Web应用的攻击"],
    "answer": 2,
    "explain": "NIDS通过分析网络流量，其传感器通常独立于被监控的主机，因此不易受到主机日志被篡改或恶意软件干扰的影响。",
    "video": "http://www.midkey.xyz"
  },
  {
    "id": 92,
    "q": "哪个术语描述了密码算法中，密文的任一微小变化应能导致明文的任一微小变化，即雪崩效应？",
    "opts": ["混淆（Confusion）", "扩散（Diffusion）", "周期性", "线性相关性"],
    "answer": 1,
    "explain": "扩散（Diffusion）是指明文或密钥的微小变化能导致密文的巨大变化，使得攻击者难以通过分析密文来推断明文或密钥。",
    "video": "http://www.midkey.xyz"
  },
  {
    "id": 93,
    "q": "以下哪种备份策略可以最快地恢复系统，但占用存储空间最大？",
    "opts": ["完整备份（Full Backup）", "增量备份（Incremental Backup）", "差分备份（Differential Backup）", "镜像备份"],
    "answer": 0,
    "explain": "完整备份每次都会复制所有选定的数据，恢复时只需一个备份集，所以恢复速度最快，但存储需求最大。",
    "video": "http://www.midkey.xyz"
  },
  {
    "id": 94,
    "q": "当进行Web应用安全测试时，测试人员向应用程序发送带有HTML或JavaScript标签的数据，是为了检测哪种漏洞？",
    "opts": ["SQL注入", "XSS", "CSRF", "DDoS"],
    "answer": 1,
    "explain": "发送带有HTML或JavaScript标签的数据是测试XSS（跨站脚本）漏洞的常用方法，看应用程序是否未对这些特殊字符进行正确的编码或转义。",
    "video": "http://www.midkey.xyz"
  },
  {
    "id": 95,
    "q": "在Windows环境中，用于查看当前活动网络连接和端口的命令行工具是？",
    "opts": ["`ipconfig`", "`ping`", "`netstat`", "`tracert`"],
    "answer": 2,
    "explain": "`netstat`命令（Network Statistics）可以显示活动的TCP连接、计算机监听的端口、网络接口统计信息等。",
    "video": "http://www.midkey.xyz"
  },
  {
    "id": 96,
    "q": "哪个协议在传输层为应用提供端到端的加密和身份验证服务？",
    "opts": ["HTTPS", "IPsec", "TLS/SSL", "S/MIME"],
    "answer": 2,
    "explain": "TLS/SSL（传输层安全协议/安全套接层）工作在传输层和应用层之间，为应用层协议（如HTTP、FTP）提供加密和身份验证。",
    "video": "http://www.midkey.xyz"
  },
  {
    "id": 97,
    "q": "以下哪种攻击利用了人类的信任和善意，而不是计算机系统的技术漏洞？",
    "opts": ["缓冲区溢出", "零日漏洞攻击", "社会工程学", "字典攻击"],
    "answer": 2,
    "explain": "社会工程学（Social Engineering）是利用人的心理弱点、好奇心或信任来骗取信息或权限的非技术性手段。",
    "video": "http://www.midkey.xyz"
  },
  {
    "id": 98,
    "q": "当一个组织决定使用加密来保护其敏感数据时，这属于哪种风险应对策略？",
    "opts": ["风险规避", "风险转移", "风险降低", "风险接受"],
    "answer": 2,
    "explain": "风险降低（Risk Reduction/Mitigation）是实施安全控制措施（如加密、防火墙）来减少风险发生的可能性或影响。",
    "video": "http://www.midkey.xyz"
  },
  {
    "id": 99,
    "q": "在密码学中，哪种概念指的是哈希函数具有的特性，即无法从哈希值逆向推导出原始输入数据？",
    "opts": ["可逆性", "抗碰撞性", "不可逆性（单向性）", "扩散性"],
    "answer": 2,
    "explain": "不可逆性（One-Way Property）是哈希函数的核心特性，确保了哈希值只能通过正向计算得到，不能通过逆向工程还原出输入。",
    "video": "http://www.midkey.xyz"
  },
  {
    "id": 100,
    "q": "哪种网络设备在网络分层模型中工作在应用层，用于检测并阻止应用层恶意流量？",
    "opts": ["路由器", "交换机", "WAF（Web应用防火墙）", "状态检测防火墙"],
    "answer": 2,
    "explain": "WAF（Web应用防火墙）是专门针对HTTP/HTTPS流量进行深度检测和过滤的，工作在OSI模型的应用层，用于防御Web应用攻击。",
    "video": "http://www.midkey.xyz"
  },


  {
    "id": 101,
    "q": "在电子商务安全中，哪种技术主要用于保障买卖双方交易信息的机密性和完整性？",
    "opts": ["ARP协议", "SMTP协议", "SSL/TLS协议", "SNMP协议"],
    "answer": 2,
    "explain": "SSL/TLS（安全套接层/传输层安全）协议通过加密和数字证书，确保了数据在客户端和服务器之间传输时的机密性和完整性。",
    "video": "http://www.midkey.xyz"
  },
  {
    "id": 102,
    "q": "以下哪个术语描述了密码体制中，密钥和明文之间的关系复杂到难以分析的特性？",
    "opts": ["混淆（Confusion）", "扩散（Diffusion）", "周期性", "线性相关性"],
    "answer": 0,
    "explain": "混淆（Confusion）是指使密钥与密文之间的关系尽可能复杂，使得攻击者难以通过密文分析推断密钥。",
    "video": "http://www.midkey.xyz"
  },
  {
    "id": 103,
    "q": "信息安全管理体系（ISMS）中，对员工进行安全意识和技能培训属于哪个控制域？",
    "opts": ["资产管理", "访问控制", "人力资源安全", "物理和环境安全"],
    "answer": 2,
    "explain": "人力资源安全（Human Resources Security）控制域涵盖了安全意识、培训和员工离职管理等相关控制措施。",
    "video": "http://www.midkey.xyz"
  },
  {
    "id": 104,
    "q": "哪种攻击利用了应用程序未能正确处理用户输入中的格式字符串，可能导致读取或写入任意内存？",
    "opts": ["缓冲区溢出", "格式字符串漏洞（Format String Bug）", "整数溢出", "逻辑漏洞"],
    "answer": 1,
    "explain": "格式字符串漏洞发生在程序使用未经验证的用户输入作为`printf`等函数的格式字符串参数时，可能导致程序崩溃或任意代码执行。",
    "video": "http://www.midkey.xyz"
  },
  {
    "id": 105,
    "q": "在非对称加密中，如果A想向B发送保密信息，A应该使用B的哪个密钥来加密？",
    "opts": ["A的私钥", "A的公钥", "B的私钥", "B的公钥"],
    "answer": 3,
    "explain": "为了确保机密性，发送方（A）使用接收方（B）的公钥加密数据，只有B的私钥才能解密。",
    "video": "http://www.midkey.xyz"
  },
  {
    "id": 106,
    "q": "下列哪项措施可以有效防御“会话劫持”（Session Hijacking）攻击？",
    "opts": ["使用MD5对密码进行哈希", "使用更复杂的密码", "为会话令牌（Session Token）设置安全标志（Secure Flag）和过期时间", "定期对服务器进行补丁更新"],
    "answer": 2,
    "explain": "会话劫持通常是通过窃取会话令牌来实现的。为令牌设置安全标志（仅通过HTTPS发送）和较短的过期时间能大幅降低风险。",
    "video": "http://www.midkey.xyz"
  },
  {
    "id": 107,
    "q": "哪个协议在传输层负责提供不可靠的、无连接的数据传输服务？",
    "opts": ["TCP", "IP", "UDP", "ARP"],
    "answer": 2,
    "explain": "UDP（User Datagram Protocol，用户数据报协议）是一种面向数据报的协议，提供快速但不保证可靠性的传输服务。",
    "video": "http://www.midkey.xyz"
  },
  {
    "id": 108,
    "q": "关于数字证书的撤销，以下哪项描述是正确的？",
    "opts": ["一旦颁发，证书就不能被撤销", "只有证书持有者可以撤销证书", "证书撤销列表（CRL）是集中查询证书状态的唯一方式", "证书可以在有效期结束前因密钥泄露等原因被CA撤销"],
    "answer": 3,
    "explain": "数字证书在有效期内，如果私钥泄露或持有者信息变更等原因，CA（认证机构）可以将其撤销，并发布在CRL或通过OCSP提供状态。",
    "video": "http://www.midkey.xyz"
  },
  {
    "id": 109,
    "q": "哪种攻击试图通过诱骗用户在Web表单中输入数据，从而窃取用户的敏感信息？",
    "opts": ["点击劫持（Clickjacking）", "键盘记录（Keylogger）", "钓鱼攻击（Phishing）", "SQL注入"],
    "answer": 2,
    "explain": "钓鱼攻击通过欺骗性网站或邮件诱使用户输入个人信息或凭证，是社会工程学的一种常见形式。",
    "video": "http://www.midkey.xyz"
  },
  {
    "id": 110,
    "q": "在灾难恢复中，用于实现业务连续性，通常在主数据中心发生灾难后，能够快速接管所有关键业务的场所是？",
    "opts": ["冷备份站点（Cold Site）", "热备份站点（Hot Site）", "暖备份站点（Warm Site）", "归档中心"],
    "answer": 1,
    "explain": "热备份站点（Hot Site）是一个完全配置和运行的备用数据中心，可以在短时间内（RTO极低）接管业务，实现业务的快速连续性。",
    "video": "http://www.midkey.xyz"
  },
  {
    "id": 111,
    "q": "哪种访问控制模型根据主体（用户）的安全级别与客体（资源）的安全级别进行比较，以确定访问权限？",
    "opts": ["DAC（自主访问控制）", "MAC（强制访问控制）", "RBAC（基于角色的访问控制）", "基于属性的访问控制（ABAC）"],
    "answer": 1,
    "explain": "MAC（Mandatory Access Control，强制访问控制）基于安全标签和规则集（如Bell-LaPadula模型），强制系统性地管理主体和客体的访问权限。",
    "video": "http://www.midkey.xyz"
  },
  {
    "id": 112,
    "q": "在云计算安全中，PaaS（平台即服务）的客户通常需要对以下哪项安全负责？",
    "opts": ["物理基础设施", "操作系统和Hypervisor", "应用配置和数据安全", "网络和存储硬件"],
    "answer": 2,
    "explain": "PaaS模型下，云厂商负责操作系统及以下的基础设施，客户则负责其部署的应用代码、配置、中间件和数据安全。",
    "video": "http://www.midkey.xyz"
  },
  {
    "id": 113,
    "q": "在渗透测试中，如果测试人员在没有被授予任何系统内部知识的情况下进行测试，这被称为？",
    "opts": ["白盒测试（White Box）", "灰盒测试（Gray Box）", "黑盒测试（Black Box）", "内部测试"],
    "answer": 2,
    "explain": "黑盒测试（Black Box Testing）模拟了外部攻击者，测试人员仅拥有公开信息，不了解目标系统的内部结构和代码。",
    "video": "http://www.midkey.xyz"
  },
  {
    "id": 114,
    "q": "下列哪项不是信息安全等级保护制度（等保）的核心要素？",
    "opts": ["定级", "备案", "密码认证", "测评"],
    "answer": 2,
    "explain": "信息安全等级保护制度的核心流程包括定级、备案、建设整改和测评。密码认证是安全技术措施的一种，但不是制度的核心环节。",
    "video": "http://www.midkey.xyz"
  },
  {
    "id": 115,
    "q": "哪种攻击利用了Web浏览器中的一个iframe，在用户不知情的情况下，诱骗用户点击了隐藏的或透明的恶意元素？",
    "opts": ["重放攻击", "点击劫持（Clickjacking）", "会话固定（Session Fixation）", "XSS"],
    "answer": 1,
    "explain": "点击劫持（Clickjacking）通过在可见页面上叠加一个透明的恶意页面，劫持用户的点击动作，使其点击恶意链接或按钮。",
    "video": "http://www.midkey.xyz"
  },
  {
    "id": 116,
    "q": "对于 Web 应用中的跨站脚本（XSS）攻击，最有效的防御手段是？",
    "opts": ["限制用户输入长度", "使用参数化查询", "对所有用户提供的输出数据进行适当的编码或转义", "部署防火墙"],
    "answer": 2,
    "explain": "XSS攻击的本质是恶意脚本在用户浏览器中执行，对用户提供的输入数据进行适当的编码或转义（Output Encoding）是防止XSS的关键。",
    "video": "http://www.midkey.xyz"
  },
  {
    "id": 117,
    "q": "在网络中，用于集中存储、管理和审计用户身份和访问权限的系统是？",
    "opts": ["LDAP/Active Directory", "DHCP", "NTP", "FTP"],
    "answer": 0,
    "explain": "LDAP（轻量级目录访问协议）和Active Directory都是目录服务，用于存储用户账户信息、安全策略和权限，实现集中化的身份管理。",
    "video": "http://www.midkey.xyz"
  },
  {
    "id": 118,
    "q": "在信息安全事件响应流程中，哪个步骤旨在将受影响的系统从网络中隔离，以防止事件蔓延？",
    "opts": ["准备（Preparation）", "遏制（Containment）", "根除（Eradication）", "恢复（Recovery）"],
    "answer": 1,
    "explain": "遏制（Containment）是事件响应的关键步骤，目的是限制安全事件的影响范围，通常通过隔离受感染系统来实现。",
    "video": "http://www.midkey.xyz"
  },
  {
    "id": 119,
    "q": "以下哪个哈希算法已被认为存在安全缺陷，不应再用于新的安全应用中？",
    "opts": ["SHA-256", "SHA-3", "MD5", "HMAC"],
    "answer": 2,
    "explain": "MD5（Message-Digest Algorithm 5）因其在碰撞攻击方面的缺陷，已不再适用于需要高安全性的应用，如数字签名和证书。",
    "video": "http://www.midkey.xyz"
  },
  {
    "id": 120,
    "q": "下列哪种技术可以用于在软件执行时，动态地监控和分析其行为，以检测恶意活动？",
    "opts": ["静态分析", "动态分析/沙箱技术", "代码审计", "逆向工程"],
    "answer": 1,
    "explain": "动态分析通过在沙箱等受控环境中运行软件，实时监控其内存访问、文件操作和网络通信等行为，以识别恶意意图。",
    "video": "http://www.midkey.xyz"
  },
  {
    "id": 121,
    "q": "哪种密钥管理技术用于在两个通信实体之间建立一个共享的秘密密钥，而不需要事先通过安全信道传输？",
    "opts": ["对称加密", "Diffie-Hellman密钥交换", "数字签名", "哈希函数"],
    "answer": 1,
    "explain": "Diffie-Hellman密钥交换（DH）允许通信双方在不安全的公共信道上安全地协商出一个共享的秘密密钥。",
    "video": "http://www.midkey.xyz"
  },
  {
    "id": 122,
    "q": "在加密通信中，如果需要同时保证数据的机密性、完整性和不可否认性，通常需要结合使用哪两种技术？",
    "opts": ["对称加密和MAC", "哈希函数和对称加密", "数字签名和公钥加密", "流密码和块密码"],
    "answer": 2,
    "explain": "公钥加密（保证机密性）和数字签名（保证完整性、认证和不可否认性）的结合使用，可以满足全面的安全需求。",
    "video": "http://www.midkey.xyz"
  },
  {
    "id": 123,
    "q": "以下哪种安全设备可以用于深度检查应用层协议内容，例如，识别并阻止特定的Web应用攻击？",
    "opts": ["L2交换机", "包过滤防火墙", "WAF（Web应用防火墙）", "路由器"],
    "answer": 2,
    "explain": "WAF专注于应用层（L7）的流量，能够理解HTTP/HTTPS协议，并进行深度内容检测来防御应用层攻击。",
    "video": "http://www.midkey.xyz"
  },
  {
    "id": 124,
    "q": "哪种攻击利用了ARP（地址解析协议）的缺陷，在局域网内将错误的MAC地址与IP地址绑定，导致流量被重定向？",
    "opts": ["DNS缓存投毒", "SYN Flood", "ARP欺骗（ARP Spoofing）", "缓冲区溢出"],
    "answer": 2,
    "explain": "ARP欺骗通过在局域网中发送伪造的ARP消息，将攻击者的MAC地址与网关或目标主机的IP地址关联，从而截获或篡改流量。",
    "video": "http://www.midkey.xyz"
  },
  {
    "id": 125,
    "q": "在Linux系统中，`chown`命令的主要作用是？",
    "opts": ["改变文件的访问权限", "改变文件的所有者和所属组", "显示文件的详细信息", "查看网络配置"],
    "answer": 1,
    "explain": "`chown`（Change Owner）命令用于更改文件或目录的所有者和/或所属组。",
    "video": "http://www.midkey.xyz"
  },
  {
    "id": 126,
    "q": "在软件安全开发中，为了避免SQL注入漏洞，开发人员应优先采用哪种编码实践？",
    "opts": ["对用户输入进行长度限制", "使用参数化查询或预编译语句", "将数据库端口设为非标准端口", "限制数据库账户的读权限"],
    "answer": 1,
    "explain": "参数化查询（Prepared Statements）将SQL代码与数据分离，是防止SQL注入的最根本和最有效的技术手段。",
    "video": "http://www.midkey.xyz"
  },
  {
    "id": 127,
    "q": "关于数字签名，下列哪项陈述是错误的？",
    "opts": ["数字签名可以提供不可否认性", "签名是使用发送方的私钥生成的", "数字签名主要用于确保数据的机密性", "接收方使用发送方的公钥验证签名"],
    "answer": 2,
    "explain": "数字签名主要用于提供数据的完整性、认证和不可否认性，而不是机密性（机密性由加密算法实现）。",
    "video": "http://www.midkey.xyz"
  },
  {
    "id": 128,
    "q": "哪种攻击利用了操作系统或应用程序在处理用户提供的整数值时，没有正确处理超出其最大或最小范围的边界情况？",
    "opts": ["缓冲区溢出", "整数溢出（Integer Overflow）", "竞态条件", "目录遍历"],
    "answer": 1,
    "explain": "整数溢出发生在对整数变量进行运算时，结果超出了变量能表示的最大范围，可能导致安全检查被绕过或缓冲区大小计算错误。",
    "video": "http://www.midkey.xyz"
  },
  {
    "id": 129,
    "q": "下列哪种密码攻击类型，攻击者可以任意选择明文进行加密，并获得相应的密文，目标是找到加密密钥？",
    "opts": ["唯密文攻击", "已知明文攻击", "选择明文攻击（Chosen-plaintext Attack）", "中间人攻击"],
    "answer": 2,
    "explain": "选择明文攻击（CPA）是攻击者对加密算法最有利的攻击方式，可以选取任意明文并获取对应的密文，这极大地简化了密钥的推导过程。",
    "video": "http://www.midkey.xyz"
  },
  {
    "id": 130,
    "q": "在物理安全中，用于防止未经授权的人员进入数据中心或机房的设备和技术是？",
    "opts": ["消防系统", "HVAC系统", "生物识别门禁和防尾随门", "UPS电源"],
    "answer": 2,
    "explain": "生物识别门禁（如指纹、虹膜）和防尾随门是防止未经授权的物理访问和防止一人刷卡多人进入的关键物理安全控制。",
    "video": "http://www.midkey.xyz"
  },
  {
    "id": 131,
    "q": "下列哪种恶意软件主要通过隐藏在合法程序中，等待被用户执行后才开始恶意活动？",
    "opts": ["蠕虫", "病毒", "特洛伊木马（Trojan Horse）", "勒索软件"],
    "answer": 2,
    "explain": "特洛伊木马（Trojan Horse）伪装成有用的或无害的程序来欺骗用户，其恶意功能隐藏在合法外表之下。",
    "video": "http://www.midkey.xyz"
  },
  {
    "id": 132,
    "q": "在密码学中，AES的密钥长度不包括以下哪一项？",
    "opts": ["128位", "192位", "256位", "512位"],
    "answer": 3,
    "explain": "AES（Advanced Encryption Standard）支持的密钥长度为128位、192位和256位，不包括512位。",
    "video": "http://www.midkey.xyz"
  },
  {
    "id": 133,
    "q": "哪种网络设备主要工作在OSI模型的第三层（网络层），用于根据IP地址转发数据包？",
    "opts": ["集线器（Hub）", "路由器（Router）", "交换机（Switch）", "网桥（Bridge）"],
    "answer": 1,
    "explain": "路由器是连接不同网络（子网）的关键设备，它通过检查数据包中的目标IP地址来决定转发路径。",
    "video": "http://www.midkey.xyz"
  },
  {
    "id": 134,
    "q": "以下哪项是实施多因素认证（MFA）的主要目的？",
    "opts": ["减少网络流量", "降低系统配置的复杂性", "通过要求两种或以上不同类型的证据来增强认证安全性", "加快用户的登录速度"],
    "answer": 2,
    "explain": "MFA要求用户提供来自不同类别的至少两个验证因素（如密码、令牌、生物特征），以大幅提高身份认证的安全性。",
    "video": "http://www.midkey.xyz"
  },
  {
    "id": 135,
    "q": "在信息安全事件响应中，对受感染系统进行彻底清除，包括删除所有恶意代码、修复漏洞的步骤是？",
    "opts": ["检测和分析", "遏制", "根除（Eradication）", "恢复"],
    "answer": 2,
    "explain": "根除（Eradication）阶段旨在消除事件的根本原因，包括清除所有恶意软件、后门和修补漏洞。",
    "video": "http://www.midkey.xyz"
  },
  {
    "id": 136,
    "q": "下列哪种技术可以用于限制应用程序在操作系统中的权限，即使应用被攻破，也能减少对系统的损害？",
    "opts": ["白名单和沙箱（Sandboxing）", "使用更长的密码", "定期进行数据备份", "物理隔离"],
    "answer": 0,
    "explain": "沙箱技术（Sandboxing）为应用程序提供了一个受限的执行环境，限制其对系统资源（如文件、网络）的访问，从而实现权限最小化。",
    "video": "http://www.midkey.xyz"
  },
  {
    "id": 137,
    "q": "哪种攻击利用了Web应用中存在的计时差异，通过测量操作的执行时间来推断敏感信息，如密码的单个字符？",
    "opts": ["侧信道攻击（Side-channel Attack）", "水坑攻击（Watering Hole）", "字典攻击", "暴力破解"],
    "answer": 0,
    "explain": "侧信道攻击（Side-channel Attack）通过分析系统执行加密或认证操作时的物理实现信息（如时间、功耗、电磁辐射）来窃取秘密信息。",
    "video": "http://www.midkey.xyz"
  },
  {
    "id": 138,
    "q": "在访问控制列表（ACL）中，下列哪种策略是“默认拒绝”（Implicit Deny）原则的体现？",
    "opts": ["明确允许所有流量，除了明确拒绝的", "在ACL的最后添加一条拒绝所有不匹配规则的流量", "只允许来自可信IP的流量", "对所有流量进行深度包检测"],
    "answer": 1,
    "explain": "默认拒绝是安全设计的核心原则，要求在ACL的末尾添加一条隐含的（或明确的）拒绝所有不匹配规则的流量的规则，以保证只有明确允许的流量才能通过。",
    "video": "http://www.midkey.xyz"
  },
  {
    "id": 139,
    "q": "哪种技术可以用于创建一个虚假的、充满漏洞的系统环境，旨在吸引和诱捕攻击者，并记录其行为？",
    "opts": ["IDS/IPS", "SIEM", "蜜罐（Honeypot）", "WAF"],
    "answer": 2,
    "explain": "蜜罐（Honeypot）是一种安全资源，其目的在于被攻击者探测、利用和入侵，以便收集攻击信息和攻击者的技术、动机。",
    "video": "http://www.midkey.xyz"
  },
  {
    "id": 140,
    "q": "在公钥基础设施（PKI）中，注册机构（RA）的主要职责是？",
    "opts": ["负责生成和保管密钥", "颁发数字证书", "验证证书申请人的身份", "维护证书撤销列表（CRL）"],
    "answer": 2,
    "explain": "RA（Registration Authority）是CA的代理，负责接收证书申请，验证申请人的身份，并将验证后的请求发送给CA。",
    "video": "http://www.midkey.xyz"
  },
  {
    "id": 141,
    "q": "下列哪个是无线网络安全协议中，目前被认为是最安全且推荐使用的标准？",
    "opts": ["WEP", "WPA", "WPA2", "WPA3"],
    "answer": 3,
    "explain": "WPA3（Wi-Fi Protected Access 3）是目前最新的无线安全标准，提供了更强的加密算法和改进的认证机制，以防御字典攻击和中间人攻击。",
    "video": "http://www.midkey.xyz"
  },
  {
    "id": 142,
    "q": "哪种攻击是针对Web应用中没有正确处理并发请求的漏洞，可能导致数据不一致或权限绕过？",
    "opts": ["缓冲区溢出", "竞态条件（Race Condition）", "XSS", "CSRF"],
    "answer": 1,
    "explain": "竞态条件（Race Condition）发生在多个进程或线程同时访问和修改共享资源时，如果操作顺序不当，就会导致不可预测的结果或安全漏洞。",
    "video": "http://www.midkey.xyz"
  },
  {
    "id": 143,
    "q": "在安全运维中，定期对操作系统和应用程序安装安全补丁，属于哪种安全控制措施？",
    "opts": ["预防性控制", "检测性控制", "恢复性控制", "威慑性控制"],
    "answer": 0,
    "explain": "安装补丁是为了消除已知的漏洞，从而防止漏洞被利用，属于预防性控制（Preventive Control）。",
    "video": "http://www.midkey.xyz"
  },
  {
    "id": 144,
    "q": "哪个协议可以用于将私有IP地址映射到公有IP地址，以实现私有网络与互联网的通信？",
    "opts": ["DHCP", "NAT", "VPN", "ICMP"],
    "answer": 1,
    "explain": "NAT（Network Address Translation，网络地址转换）允许私有网络中的多台设备共享一个或少数几个公有IP地址访问互联网。",
    "video": "http://www.midkey.xyz"
  },
  {
    "id": 145,
    "q": "在安全事件响应过程中，以下哪一步骤是收集和分析数据，以确定事件发生的原因、范围和影响？",
    "opts": ["遏制", "分析（Analysis）", "恢复", "事后总结"],
    "answer": 1,
    "explain": "分析阶段通过检查日志、内存转储、磁盘镜像等数据，来确定攻击者的活动、使用的技术和事件的全部范围。",
    "video": "http://www.midkey.xyz"
  },
  {
    "id": 146,
    "q": "哪种加密算法被设计用于加密单个位或字节的数据流，而不是数据块？",
    "opts": ["块密码（Block Cipher）", "流密码（Stream Cipher）", "RSA", "Diffie-Hellman"],
    "answer": 1,
    "explain": "流密码（Stream Cipher）是一种对称加密算法，它将明文的位流与密钥流按位异或来生成密文，适用于实时通信。",
    "video": "http://www.midkey.xyz"
  },
  {
    "id": 147,
    "q": "在Web应用中，`HttpOnly` Cookie标志的主要目的是防止哪种攻击窃取会话令牌？",
    "opts": ["CSRF", "XSS", "SQL注入", "DoS"],
    "answer": 1,
    "explain": "`HttpOnly`标志阻止客户端脚本（如JavaScript）访问Cookie，从而有效防止XSS攻击窃取会话令牌。",
    "video": "http://www.midkey.xyz"
  },
  {
    "id": 148,
    "q": "为了确保数据在备份后仍保持机密性，最合适的措施是？",
    "opts": ["将备份数据存储在防火墙内", "对备份数据进行加密", "设置复杂的备份密码", "定期检查备份介质的物理安全"],
    "answer": 1,
    "explain": "对备份数据进行加密是防止存储介质被盗或泄露时，数据内容被未授权方读取的最有效方法。",
    "video": "http://www.midkey.xyz"
  },
  {
    "id": 149,
    "q": "下列哪种安全设计原则主张，系统应在安全策略失败时提供额外的保护层？",
    "opts": ["纵深防御（Defense in Depth）", "最小权限原则", "故障安全原则", "安全隔离原则"],
    "answer": 0,
    "explain": "纵深防御（Defense in Depth）要求部署多层、冗余的安全控制措施，即使其中一层被突破，其他层也能提供保护。",
    "video": "http://www.midkey.xyz"
  },
  {
    "id": 150,
    "q": "在Linux系统中，用于配置和管理内核级网络包过滤规则的工具是？",
    "opts": ["`ifconfig`", "`iptables` / `nftables`", "`route`", "`netstat`"],
    "answer": 1,
    "explain": "`iptables`（或较新的`nftables`）是Linux环境下用于配置内核防火墙（Netfilter）规则集的主要命令行工具。",
    "video": "http://www.midkey.xyz"
  },


  {
    "id": 151,
    "q": "在Web安全中，哪个漏洞允许攻击者通过URL参数或POST数据注入外部链接，诱使用户或服务器向外部资源发起请求？",
    "opts": ["CSRF", "XSS", "SSRF（服务器端请求伪造）", "RCE"],
    "answer": 2,
    "explain": "SSRF（Server-Side Request Forgery）漏洞利用服务器发起对外请求的功能，诱使服务器访问外部恶意地址或内网资源。",
    "video": "http://www.midkey.xyz"
  },
  {
    "id": 152,
    "q": "以下哪项是确保数据完整性的主要技术手段？",
    "opts": ["加密", "身份认证", "数字签名或哈希校验", "访问控制"],
    "answer": 2,
    "explain": "数字签名和哈希校验（如MD5, SHA-256）通过计算数据的唯一摘要，来验证数据在传输或存储过程中是否被篡改。",
    "video": "http://www.midkey.xyz"
  },
  {
    "id": 153,
    "q": "在对称加密模式中，哪种模式需要使用初始化向量（IV）来确保每个消息块的加密过程都是唯一的，即使明文相同？",
    "opts": ["ECB（电码本模式）", "CBC（密文分组链接模式）", "CTR（计数器模式）", "ECB与CBC均需要"],
    "answer": 1,
    "explain": "CBC（Cipher Block Chaining）模式使用初始化向量（IV）对第一个明文块进行加密，并将上一个密文块作为输入异或到下一个明文块，防止重复模式出现。",
    "video": "http://www.midkey.xyz"
  },
  {
    "id": 154,
    "q": "以下哪种攻击旨在通过耗尽网络带宽、系统内存或CPU资源，导致服务对合法用户不可用？",
    "opts": ["钓鱼攻击", "拒绝服务攻击（DoS/DDoS）", "会话劫持", "零日攻击"],
    "answer": 1,
    "explain": "拒绝服务攻击（Denial of Service）的目标是使目标系统或网络资源耗尽，从而阻止合法用户访问服务。",
    "video": "http://www.midkey.xyz"
  },
  {
    "id": 155,
    "q": "下列哪项关于“零日漏洞”（Zero-day Vulnerability）的描述是正确的？",
    "opts": ["是指刚被发现，尚未发布补丁或防御措施的漏洞", "是指已存在十年以上的、未被修复的漏洞", "是病毒感染系统后隐藏自身所用的技术", "是针对操作系统内核的特殊攻击"],
    "answer": 0,
    "explain": "零日漏洞（Zero-day）是指厂商尚未发布补丁，或者漏洞信息还未公开，但已被攻击者利用的软件漏洞。",
    "video": "http://www.midkey.xyz"
  },
  {
    "id": 156,
    "q": "在身份认证中，哪种认证因素属于“你拥有什么”（Something You Have）？",
    "opts": ["指纹", "动态令牌（Token）", "口令", "虹膜"],
    "answer": 1,
    "explain": "动态令牌属于用户拥有的物品，用于生成一次性密码（OTP），以证明用户身份。",
    "video": "http://www.midkey.xyz"
  },
  {
    "id": 157,
    "q": "信息安全风险分析过程中，计算风险等级（Risk Level）时主要考虑哪两个维度？",
    "opts": ["技术难度和成本", "影响（Impact）和可能性（Likelihood）", "RTO和RPO", "资产价值和威胁数量"],
    "answer": 1,
    "explain": "风险等级通常定义为：风险等级 = 威胁发生的可能性 × 威胁造成的影响。",
    "video": "http://www.midkey.xyz"
  },
  {
    "id": 158,
    "q": "哪种安全设备可以工作在网络边界，用于根据预定义的规则集（如IP地址、端口）过滤网络流量？",
    "opts": ["路由器", "交换机", "防火墙", "负载均衡器"],
    "answer": 2,
    "explain": "防火墙是网络安全边界的核心组件，负责根据配置的安全策略过滤进出网络的流量。",
    "video": "http://www.midkey.xyz"
  },
  {
    "id": 159,
    "q": "在公钥基础设施（PKI）中，私钥应该由谁安全保管？",
    "opts": ["认证机构（CA）", "注册机构（RA）", "密钥托管中心", "证书持有者"],
    "answer": 3,
    "explain": "私钥是用户的秘密凭证，必须由证书持有者负责安全保管，任何人（包括CA）都不应该知晓用户的私钥。",
    "video": "http://www.midkey.xyz"
  },
  {
    "id": 160,
    "q": "以下哪种攻击利用了Web应用对用户提交的会话令牌没有进行有效验证，使得攻击者可以利用预设的会话ID？",
    "opts": ["会话固定（Session Fixation）", "点击劫持", "SQL注入", "XSS"],
    "answer": 0,
    "explain": "会话固定攻击中，攻击者预先设置一个有效的会话ID，诱骗用户使用该ID登录，从而劫持该会话。",
    "video": "http://www.midkey.xyz"
  },
  {
    "id": 161,
    "q": "在Linux操作系统中，哪个目录通常用于存放系统或应用程序的日志文件？",
    "opts": ["`/etc`", "`/bin`", "`/var/log`", "`/home`"],
    "answer": 2,
    "explain": "`/var/log`是Linux文件系统层次结构标准（FHS）中指定的用于存放系统和应用日志文件的目录。",
    "video": "http://www.midkey.xyz"
  },
  {
    "id": 162,
    "q": "哪种技术可以用于创建用户身份的假名，从而保护其真实身份信息，例如在测试环境中？",
    "opts": ["数据加密", "数据备份", "数据脱敏/假名化（Pseudonymization）", "数据压缩"],
    "answer": 2,
    "explain": "假名化（Pseudonymization）是数据脱敏的一种形式，用一个或多个假名替换数据中的身份标识符，使其在不查看额外信息的情况下无法识别个体。",
    "video": "http://www.midkey.xyz"
  },
  {
    "id": 163,
    "q": "在安全软件开发中，安全代码审计应该在哪个阶段进行？",
    "opts": ["需求分析阶段", "设计阶段", "编码实现和测试阶段", "系统发布后"],
    "answer": 2,
    "explain": "安全代码审计（Code Review）主要在编码和测试阶段进行，以发现并修复代码中的安全缺陷和漏洞。",
    "video": "http://www.midkey.xyz"
  },
  {
    "id": 164,
    "q": "在网络安全审计中，哪个工具最适合用于对一个开放端口的服务（如Web服务器）进行漏洞扫描和安全评估？",
    "opts": ["Wireshark", "Nessus/OpenVAS", "Nmap", "Metasploit"],
    "answer": 1,
    "explain": "Nessus和OpenVAS是成熟的漏洞扫描工具，能够检测主机、操作系统和应用程序中存在的已知安全漏洞。",
    "video": "http://www.midkey.xyz"
  },
  {
    "id": 165,
    "q": "下列哪个是基于Kerberos协议实现的单点登录（SSO）系统中的核心组件，负责发放票据授予票据（TGT）？",
    "opts": ["密钥分发中心（KDC）", "应用服务器", "客户端", "身份提供者（IdP）"],
    "answer": 0,
    "explain": "Kerberos的KDC（Key Distribution Center）是核心组件，它包含认证服务器（AS）和票据授予服务器（TGS）。TGS负责向用户发放服务票据。",
    "video": "http://www.midkey.xyz"
  },
  {
    "id": 166,
    "q": "哪种攻击利用了DHCP（动态主机配置协议）的缺陷，通过伪造DHCP服务器，向客户端分配错误的IP地址和网关？",
    "opts": ["DNS劫持", "DHCP饥饿攻击", "DHCP欺骗（DHCP Spoofing）", "ARP欺骗"],
    "answer": 2,
    "explain": "DHCP欺骗中，攻击者假冒DHCP服务器，向网络中的客户端提供伪造的配置信息（如网关IP），从而将客户端流量重定向到攻击者。",
    "video": "http://www.midkey.xyz"
  },
  {
    "id": 167,
    "q": "在安全管理中，以下哪项属于“威慑性控制”（Deterrent Control）？",
    "opts": ["安装防火墙", "灾难恢复计划", "清晰的惩戒措施或法律声明", "定期进行漏洞扫描"],
    "answer": 2,
    "explain": "威慑性控制旨在通过警告、声明或惩罚措施来阻止攻击者或内部人员采取恶意行为。",
    "video": "http://www.midkey.xyz"
  },
  {
    "id": 168,
    "q": "在公钥加密体制中，如果Alice想要对一条消息进行数字签名，她应该使用自己的哪个密钥？",
    "opts": ["Alice的私钥", "Alice的公钥", "Bob的私钥", "Bob的公钥"],
    "answer": 0,
    "explain": "数字签名是为了证明发送方（Alice）的身份和不可否认性，因此她必须使用自己独有的私钥进行加密签名。",
    "video": "http://www.midkey.xyz"
  },
  {
    "id": 169,
    "q": "在信息安全管理体系中，风险分析的目的是什么？",
    "opts": ["制定组织的年度安全预算", "识别威胁、漏洞和资产价值，并量化风险等级", "确定系统的硬件和软件需求", "招聘专业安全人员"],
    "answer": 1,
    "explain": "风险分析是风险管理的第一步，旨在系统性地识别和评估组织面临的安全风险，以便后续进行处理。",
    "video": "http://www.midkey.xyz"
  },
  {
    "id": 170,
    "q": "哪种攻击利用了Web应用在处理用户输入时没有正确处理特殊字符，导致攻击者可以控制SQL查询逻辑？",
    "opts": ["XSS", "CSRF", "SQL注入", "RCE"],
    "answer": 2,
    "explain": "SQL注入中，攻击者在输入字段中插入SQL命令片段，欺骗数据库执行非预期的查询。",
    "video": "http://www.midkey.xyz"
  },
  {
    "id": 171,
    "q": "以下哪种攻击试图通过拦截和修改两个通信实体之间的加密密钥协商过程，从而窃听或篡改数据？",
    "opts": ["中间人攻击（MITM）", "重放攻击", "字典攻击", "暴力破解"],
    "answer": 0,
    "explain": "中间人攻击（MITM）发生在两个通信方之间，攻击者秘密地拦截、中继和可能修改彼此发送的消息。",
    "video": "http://www.midkey.xyz"
  },
  {
    "id": 172,
    "q": "在Linux系统中，用于查看和控制用户对文件访问权限的命令是？",
    "opts": ["`chown`", "`netstat`", "`chmod`", "`ls -l`"],
    "answer": 2,
    "explain": "`chmod`命令（Change Mode）用于改变文件或目录的访问权限（读、写、执行）。",
    "video": "http://www.midkey.xyz"
  },
  {
    "id": 173,
    "q": "在云计算环境中，责任共担模型中，哪种服务模型给予客户对安全配置的最大控制权？",
    "opts": ["SaaS（软件即服务）", "PaaS（平台即服务）", "IaaS（基础设施即服务）", "FaaS（功能即服务）"],
    "answer": 2,
    "explain": "IaaS（Infrastructure as a Service）模型下，客户负责管理和安全配置操作系统、应用、运行时等，拥有最大的控制权。",
    "video": "http://www.midkey.xyz"
  },
  {
    "id": 174,
    "q": "哪种备份策略只备份自上次完整备份以来发生变化的数据？",
    "opts": ["完整备份", "差分备份（Differential Backup）", "增量备份（Incremental Backup）", "镜像备份"],
    "answer": 1,
    "explain": "差分备份（Differential Backup）备份自上次完整备份以来所有发生变化的数据，恢复时只需要最新一次完整备份和最新一次差分备份。",
    "video": "http://www.midkey.xyz"
  },
  {
    "id": 175,
    "q": "以下哪个标准提供了信息安全控制措施的详细指南和建议？",
    "opts": ["ISO/IEC 27001", "ISO/IEC 27002", "ISO 9001", "GB/T 22080"],
    "answer": 1,
    "explain": "ISO/IEC 27002是ISO/IEC 27001的配套标准，提供了关于如何实施信息安全控制措施的实用指南和最佳实践。",
    "video": "http://www.midkey.xyz"
  },
  {
    "id": 176,
    "q": "哪种攻击利用了网络会话中的弱点，通过窃取或预测会话ID，冒充合法用户进行操作？",
    "opts": ["CSRF", "XSS", "会话劫持（Session Hijacking）", "端口扫描"],
    "answer": 2,
    "explain": "会话劫持（Session Hijacking）通过获取或猜测有效的会话ID，使攻击者能够接管用户与Web服务器之间的会话。",
    "video": "http://www.midkey.xyz"
  },
  {
    "id": 177,
    "q": "下列哪种身份验证方法被认为具有最高的安全性，通常用于高级别的安全要求？",
    "opts": ["单因素口令认证", "双因素认证（MFA）", "生物特征识别", "使用静态PIN码"],
    "answer": 1,
    "explain": "双因素认证（MFA）通过结合两种不同类型的身份验证因素（如密码+令牌），大大提高了认证的安全性，是最推荐的认证方式。",
    "video": "http://www.midkey.xyz"
  },
  {
    "id": 178,
    "q": "以下哪个术语描述了恶意软件通过自我复制，并利用网络漏洞快速传播的能力？",
    "opts": ["病毒", "特洛伊木马", "蠕虫（Worm）", "间谍软件"],
    "answer": 2,
    "explain": "蠕虫（Worm）能够独立运行，利用网络协议和软件漏洞进行自我复制和传播，而无需寄生于其他程序。",
    "video": "http://www.midkey.xyz"
  },
  {
    "id": 179,
    "q": "在安全运维中，部署蜜罐（Honeypot）的主要目的是什么？",
    "opts": ["提供业务服务的高可用性", "充当第二道防火墙", "收集攻击者的信息和入侵方法", "对所有网络流量进行加密"],
    "answer": 2,
    "explain": "蜜罐是一个被故意设计成易受攻击的系统，其唯一目的是吸引攻击者并详细记录他们的活动，以用于研究和威胁情报收集。",
    "video": "http://www.midkey.xyz"
  },
  {
    "id": 180,
    "q": "哪种协议可以用于在电子邮件中提供加密和数字签名服务，从而增强邮件安全？",
    "opts": ["POP3", "IMAP", "S/MIME 或 PGP", "HTTP"],
    "answer": 2,
    "explain": "S/MIME（Secure/Multipurpose Internet Mail Extensions）和PGP（Pretty Good Privacy）是用于加密和数字签名电子邮件内容的标准协议。",
    "video": "http://www.midkey.xyz"
  },
  {
    "id": 181,
    "q": "以下哪种攻击利用了Web应用对用户提供的数据未进行正确验证，导致攻击者可以执行任意操作系统命令？",
    "opts": ["SQL注入", "文件上传漏洞", "远程代码执行（RCE）", "XSS"],
    "answer": 2,
    "explain": "远程代码执行（RCE）是最严重的漏洞之一，它允许攻击者远程在服务器上执行任意操作系统命令，完全控制目标系统。",
    "video": "http://www.midkey.xyz"
  },
  {
    "id": 182,
    "q": "在密码学中，AES属于哪种类型的加密算法？",
    "opts": ["公钥加密", "哈希函数", "对称块密码", "数字签名算法"],
    "answer": 2,
    "explain": "AES（Advanced Encryption Standard）是使用单个密钥进行加密和解密的对称块密码算法。",
    "video": "http://www.midkey.xyz"
  },
  {
    "id": 183,
    "q": "在PKI体系中，证书撤销列表（CRL）的主要作用是？",
    "opts": ["存储所有颁发的有效证书", "用于验证证书的有效性", "列出已被撤销或不再信任的证书", "生成公钥和私钥对"],
    "answer": 2,
    "explain": "CRL（Certificate Revocation List）是由CA定期发布的列表，包含所有在有效期内但已被撤销的数字证书的序列号。",
    "video": "http://www.midkey.xyz"
  },
  {
    "id": 184,
    "q": "在Windows环境中，用于查看和管理系统、应用和安全事件日志的工具是？",
    "opts": ["任务管理器", "注册表编辑器", "事件查看器（Event Viewer）", "命令行工具"],
    "answer": 2,
    "explain": "事件查看器（Event Viewer）是Windows系统中用于集中查看、分析和管理各类系统事件和安全日志的工具。",
    "video": "http://www.midkey.xyz"
  },
  {
    "id": 185,
    "q": "在网络分层模型中，哪个协议工作在应用层，用于向Web服务器请求资源？",
    "opts": ["TCP", "IP", "HTTP/HTTPS", "ARP"],
    "answer": 2,
    "explain": "HTTP（超文本传输协议）和HTTPS是Web浏览器和服务器之间用于传输数据的应用层协议。",
    "video": "http://www.midkey.xyz"
  },
  {
    "id": 186,
    "q": "下列哪项不是信息安全策略中应包含的关键内容？",
    "opts": ["安全目标和范围", "员工的惩戒措施", "资产的价值和敏感度", "安全控制措施的详细配置"],
    "answer": 3,
    "explain": "安全策略应是高层次、指导性的文件。详细的技术配置通常属于安全标准或操作规程，而非策略本身。",
    "video": "http://www.midkey.xyz"
  },
  {
    "id": 187,
    "q": "以下哪种攻击旨在通过伪装成同一网络中的合法主机，窃听或篡改数据流量？",
    "opts": ["钓鱼攻击", "内部拒绝服务攻击", "ARP欺骗", "外部网络渗透"],
    "answer": 2,
    "explain": "ARP欺骗（ARP Spoofing）是一种内部网络攻击，通过伪造ARP响应来欺骗其他主机，将流量重定向到攻击者。",
    "video": "http://www.midkey.xyz"
  },
  {
    "id": 188,
    "q": "在密码学中，哪种技术用于在不安全的信道上，验证消息的发送者身份和消息的完整性？",
    "opts": ["数字签名", "对称加密", "流密码", "哈希函数"],
    "answer": 0,
    "explain": "数字签名结合了哈希函数和非对称加密，可以同时提供认证、完整性和不可否认性。",
    "video": "http://www.midkey.xyz"
  },
  {
    "id": 189,
    "q": "在云计算安全中，如果客户担心云服务提供商（CSP）的硬件存在漏洞，这属于哪种安全风险？",
    "opts": ["软件漏洞风险", "供应链风险", "合规风险", "网络配置风险"],
    "answer": 1,
    "explain": "云计算环境中的硬件和底层基础设施通常由CSP的供应商提供，因此这属于供应链（Supply Chain）安全风险。",
    "video": "http://www.midkey.xyz"
  },
  {
    "id": 190,
    "q": "在信息安全事件响应中，哪个步骤旨在将系统恢复到正常运作状态，并在网络中重新部署？",
    "opts": ["遏制", "根除", "恢复（Recovery）", "事后总结"],
    "answer": 2,
    "explain": "恢复（Recovery）阶段包括系统重建、数据恢复、部署到生产环境，并进行必要的验证和监控。",
    "video": "http://www.midkey.xyz"
  },
  {
    "id": 191,
    "q": "哪种攻击利用了应用程序在处理大量输入数据时，没有正确地检查边界，导致程序运行异常或崩溃？",
    "opts": ["SQL注入", "缓冲区溢出", "逻辑漏洞", "目录遍历"],
    "answer": 1,
    "explain": "缓冲区溢出（Buffer Overflow）是由于程序对输入数据的长度未进行严格限制，导致数据写入超过分配的缓冲区，覆盖了相邻的内存。",
    "video": "http://www.midkey.xyz"
  },
  {
    "id": 192,
    "q": "在安全管理中，定期对所有员工进行钓鱼邮件模拟测试，属于哪种安全控制措施？",
    "opts": ["物理控制", "技术控制", "管理控制", "威慑控制"],
    "answer": 2,
    "explain": "员工培训、策略制定、测试和流程管理等都属于管理控制（Administrative Controls）的范畴。",
    "video": "http://www.midkey.xyz"
  },
  {
    "id": 193,
    "q": "在WPA3无线安全协议中，引入了哪个特性来增强对离线字典攻击的防御？",
    "opts": ["TKIP", "CCMP", "SAE（同步身份验证交换）", "WEP"],
    "answer": 2,
    "explain": "WPA3引入了SAE（Simultaneous Authentication of Equals，同步身份验证交换）来取代WPA2的PSK（预共享密钥），可以有效抵抗离线字典攻击。",
    "video": "http://www.midkey.xyz"
  },
  {
    "id": 194,
    "q": "哪个协议在传输层提供面向连接的、可靠的数据传输服务？",
    "opts": ["IP", "TCP", "UDP", "ICMP"],
    "answer": 1,
    "explain": "TCP（Transmission Control Protocol，传输控制协议）通过三次握手建立连接，提供流量控制和重传机制，保证数据可靠传输。",
    "video": "http://www.midkey.xyz"
  },
  {
    "id": 195,
    "q": "在渗透测试的各个阶段中，使用Nmap等工具扫描开放端口和收集服务版本信息，属于哪个阶段？",
    "opts": ["信息收集/侦察", "漏洞分析", "攻击/利用", "清理"],
    "answer": 0,
    "explain": "信息收集/侦察阶段是渗透测试的第一步，旨在尽可能多地收集关于目标系统的公开信息，包括网络结构、开放端口和服务信息。",
    "video": "http://www.midkey.xyz"
  },
  {
    "id": 196,
    "q": "以下哪项是确保数据可用性的主要措施？",
    "opts": ["数据加密", "最小权限原则", "冗余和备份策略", "哈希校验"],
    "answer": 2,
    "explain": "数据可用性（Availability）是指授权用户在需要时能够访问数据和资源，冗余和备份策略是实现高可用性的关键。",
    "video": "http://www.midkey.xyz"
  },
  {
    "id": 197,
    "q": "哪种技术可以用于限制Web应用中跨站请求伪造（CSRF）攻击？",
    "opts": ["在响应头中设置`HttpOnly` Cookie", "使用参数化查询", "在关键请求中使用CSRF Token或`SameSite` Cookie属性", "对所有用户输入进行编码"],
    "answer": 2,
    "explain": "CSRF Token确保请求来自合法的Web应用，`SameSite` Cookie属性限制了跨域发送Cookie，是防御CSRF的主要手段。",
    "video": "http://www.midkey.xyz"
  },
  {
    "id": 198,
    "q": "在公钥基础设施（PKI）中，哪种实体负责验证数字证书是否有效，并提供在线状态查询？",
    "opts": ["CRL（证书撤销列表）", "OCSP响应者", "证书持有者", "CA（认证机构）"],
    "answer": 1,
    "explain": "OCSP（Online Certificate Status Protocol，在线证书状态协议）响应者提供证书的实时有效性查询，比CRL更及时。",
    "video": "http://www.midkey.xyz"
  },
  {
    "id": 199,
    "q": "在安全架构设计中，将不同的安全功能（如防火墙、IDS、WAF）部署在网络的不同位置，以提供多层保护，体现了哪种原则？",
    "opts": ["最小特权原则", "纵深防御（Defense in Depth）", "故障安全原则", "隔离原则"],
    "answer": 1,
    "explain": "纵深防御（Defense in Depth）通过在多个层次上部署安全控制措施，确保即使某一控制被绕过，其他控制也能发挥作用。",
    "video": "http://www.midkey.xyz"
  },
  {
    "id": 200,
    "q": "下列哪种加密模式是流密码的一种实现，通常用于高性能和并行处理的场景？",
    "opts": ["CBC", "ECB", "CFB", "CTR"],
    "answer": 3,
    "explain": "CTR（Counter Mode，计数器模式）将块密码转换为流密码，支持数据的并行加密和解密，广泛用于高性能应用。",
    "video": "http://www.midkey.xyz"
  }
]